torchdrug/__init__.py
torchdrug/patch.py
torchdrug/core/__init__.py
torchdrug/core/core.py
torchdrug/core/engine.py
torchdrug/core/logger.py
torchdrug/core/meter.py
torchdrug/data/__init__.py
torchdrug/data/constant.py
torchdrug/data/dataloader.py
torchdrug/data/dataset.py
torchdrug/data/dictionary.py
torchdrug/data/feature.py
torchdrug/data/graph.py
torchdrug/data/molecule.py
torchdrug/data/protein.py
torchdrug/data/rdkit/__init__.py
torchdrug/data/rdkit/draw.py
torchdrug/datasets/__init__.py
torchdrug/datasets/alphafolddb.py
torchdrug/datasets/bace.py
torchdrug/datasets/bbbp.py
torchdrug/datasets/beta_lactamase.py
torchdrug/datasets/binary_localization.py
torchdrug/datasets/bindingdb.py
torchdrug/datasets/cep.py
torchdrug/datasets/chembl_filtered.py
torchdrug/datasets/citeseer.py
torchdrug/datasets/clintox.py
torchdrug/datasets/cora.py
torchdrug/datasets/delaney.py
torchdrug/datasets/enzyme_commission.py
torchdrug/datasets/fb15k.py
torchdrug/datasets/fluorescence.py
torchdrug/datasets/fold.py
torchdrug/datasets/freesolv.py
torchdrug/datasets/gene_ontology.py
torchdrug/datasets/hetionet.py
torchdrug/datasets/hiv.py
torchdrug/datasets/human_ppi.py
torchdrug/datasets/lipophilicity.py
torchdrug/datasets/malaria.py
torchdrug/datasets/moses.py
torchdrug/datasets/muv.py
torchdrug/datasets/opv.py
torchdrug/datasets/pcqm4m.py
torchdrug/datasets/pdbbind.py
torchdrug/datasets/ppi_affinity.py
torchdrug/datasets/proteinnet.py
torchdrug/datasets/pubchem110m.py
torchdrug/datasets/pubmed.py
torchdrug/datasets/qm8.py
torchdrug/datasets/qm9.py
torchdrug/datasets/secondary_structure.py
torchdrug/datasets/sider.py
torchdrug/datasets/solubility.py
torchdrug/datasets/stability.py
torchdrug/datasets/subcellular_localization.py
torchdrug/datasets/tox21.py
torchdrug/datasets/toxcast.py
torchdrug/datasets/uspto50k.py
torchdrug/datasets/wn18.py
torchdrug/datasets/yeast_ppi.py
torchdrug/datasets/zinc250k.py
torchdrug/datasets/zinc2m.py
torchdrug/layers/__init__.py
torchdrug/layers/block.py
torchdrug-0.2.0.post1.dist-info/LICENSE
torchdrug-0.2.0.post1.dist-info/METADATA
torchdrug-0.2.0.post1.dist-info/WHEEL
torchdrug-0.2.0.post1.dist-info/top_level.txt
torchdrug-0.2.0.post1.dist-info/RECORD
