Metadata-Version: 2.1
Name: torchdrug
Version: 0.2.0.post1
Summary: A powerful and flexible machine learning platform for drug discovery
Home-page: https://torchdrug.ai/
Author: TorchDrug Team
License: Apache-2.0
Keywords: deep-learning,pytorch,drug-discovery
Classifier: Development Status :: 4 - Beta
Classifier: Intended Audience :: Developers
Classifier: Intended Audience :: Science/Research
Classifier: License :: OSI Approved :: Apache Software License
Classifier: Topic :: Scientific/Engineering :: Mathematics
Classifier: Topic :: Scientific/Engineering :: Artificial Intelligence
Classifier: Topic :: Software Development :: Libraries
Classifier: Programming Language :: Python :: 3
Requires-Python: >=3.7,<3.10
License-File: LICENSE
Requires-Dist: torch (>=1.8.0)
Requires-Dist: torch-scatter (>=2.0.8)
Requires-Dist: torch-cluster (>=1.5.9)
Requires-Dist: decorator
Requires-Dist: numpy (>=1.11)
Requires-Dist: rdkit-pypi (>=2020.9)
Requires-Dist: matplotlib
Requires-Dist: tqdm
Requires-Dist: networkx
Requires-Dist: ninja
Requires-Dist: jinja2
Requires-Dist: lmdb
Requires-Dist: fair-esm
